myair_py/__init__.py
myair_py/legacy_client.py
myair_py/myair_client.py
myair_py/new_client.py
myair_py-0.1.1.dist-info/LICENSE
myair_py-0.1.1.dist-info/METADATA
myair_py-0.1.1.dist-info/WHEEL
myair_py-0.1.1.dist-info/RECORD
